ursine/__init__.py
ursine/header.py
ursine/header_parsing.py
ursine/uri.py
ursine/uri_parsing.py
ursine-0.3.1.dist-info/LICENSE.txt
ursine-0.3.1.dist-info/METADATA
ursine-0.3.1.dist-info/RECORD
ursine-0.3.1.dist-info/WHEEL
ursine-0.3.1.dist-info/top_level.txt
